pylint_django/__init__.py
pylint_django/__pkginfo__.py
pylint_django/compat.py
pylint_django/plugin.py
pylint_django/utils.py
pylint_django/augmentations/__init__.py
pylint_django/checkers/__init__.py
pylint_django/checkers/auth_user.py
pylint_django/checkers/django_installed.py
pylint_django/checkers/foreign_key_strings.py
pylint_django/checkers/forms.py
pylint_django/checkers/json_response.py
pylint_django/checkers/migrations.py
pylint_django/checkers/models.py
pylint_django/tests/__init__.py
pylint_django/tests/settings.py
pylint_django/tests/test_django_not_installed.sh
pylint_django/tests/test_func.py
pylint_django/tests/testing_pylint.rc
pylint_django/tests/input/__init__.py
pylint_django/tests/input/external_django_tables2_noerror_meta_class.py
pylint_django/tests/input/external_drf_noerror_serializer.py
pylint_django/tests/input/external_drf_noerror_serializer.rc
pylint_django/tests/input/external_factory_boy_noerror.py
pylint_django/tests/input/external_factory_boy_noerror.rc
pylint_django/tests/input/external_model_utils_noerror_override_manager.py
pylint_django/tests/input/external_model_utils_noerror_override_manager.rc
pylint_django/tests/input/external_psycopg2_noerror_postgres_fields.py
pylint_django/tests/input/external_psycopg2_noerror_postgres_fields.rc
pylint_django/tests/input/external_tastypie_noerror_foreign_key.py
pylint_django/tests/input/func_hard_coded_auth_user.py
pylint_django/tests/input/func_hard_coded_auth_user.txt
pylint_django/tests/input/func_json_response.py
pylint_django/tests/input/func_json_response.txt
pylint_django/tests/input/func_model_does_not_use_unicode_py33.py
pylint_django/tests/input/func_model_does_not_use_unicode_py33.txt
pylint_django/tests/input/func_model_no_explicit_unicode_str_compat.py
pylint_django/tests/input/func_model_no_explicit_unicode_str_compat.txt
pylint_django/tests/input/func_modelform_exclude.py
pylint_django/tests/input/func_modelform_exclude.txt
pylint_django-2.5.3.dist-info/LICENSE
pylint_django-2.5.3.dist-info/METADATA
pylint_django-2.5.3.dist-info/WHEEL
pylint_django-2.5.3.dist-info/top_level.txt
pylint_django-2.5.3.dist-info/RECORD
