Metadata-Version: 2.1
Name: pylint-django
Version: 2.5.3
Summary: A Pylint plugin to help Pylint understand the Django web framework
Home-page: https://github.com/PyCQA/pylint-django
Author: landscape.io
Author-email: code@landscape.io
License: GPLv2
Project-URL: Changelog, https://github.com/PyCQA/pylint-django/blob/master/CHANGELOG.rst
Keywords: pylint,django,plugin
Platform: UNKNOWN
Classifier: Environment :: Console
Classifier: Intended Audience :: Developers
Classifier: Operating System :: Unix
Classifier: Topic :: Software Development :: Quality Assurance
Classifier: Programming Language :: Python :: 3
Classifier: Programming Language :: Python :: 3.6
Classifier: Programming Language :: Python :: 3.7
Classifier: Programming Language :: Python :: 3.8
Classifier: Programming Language :: Python :: 3.9
Classifier: Framework :: Django :: 1.11
Classifier: Framework :: Django :: 2.0
Classifier: Framework :: Django :: 2.2
Classifier: Framework :: Django :: 3.0
Classifier: Framework :: Django :: 3.1
Classifier: Framework :: Django :: 3.2
Provides-Extra: with_django
Provides-Extra: for_tests
License-File: LICENSE
